estat_api_dlt_helper/__init__.py
estat_api_dlt_helper/py.typed
estat_api_dlt_helper/api/__init__.py
estat_api_dlt_helper/api/client.py
estat_api_dlt_helper/api/endpoints.py
estat_api_dlt_helper/config/__init__.py
estat_api_dlt_helper/config/models.py
estat_api_dlt_helper/loader/__init__.py
estat_api_dlt_helper/loader/dlt_pipeline.py
estat_api_dlt_helper/loader/dlt_resource.py
estat_api_dlt_helper/loader/load_manager.py
estat_api_dlt_helper/loader/unified_schema_resource.py
estat_api_dlt_helper/models/__init__.py
estat_api_dlt_helper/models/estat_models.py
estat_api_dlt_helper/models/unified_schema.py
estat_api_dlt_helper/parser/__init__.py
estat_api_dlt_helper/parser/arrow_converter.py
estat_api_dlt_helper/parser/metadata_processor.py
estat_api_dlt_helper/parser/response_parser.py
estat_api_dlt_helper/utils/__init__.py
estat_api_dlt_helper/utils/arrow_utils.py
estat_api_dlt_helper/utils/logging.py
estat_api_dlt_helper-0.1.4.dist-info/METADATA
estat_api_dlt_helper-0.1.4.dist-info/WHEEL
estat_api_dlt_helper-0.1.4.dist-info/licenses/LICENSE
estat_api_dlt_helper-0.1.4.dist-info/RECORD
