Metadata-Version: 2.4
Name: estat-api-dlt-helper
Version: 0.1.4
Summary: e-Stat APIを使ってデータを取得し、dltを使ってデータをロードするためのヘルパーライブラリ
Project-URL: Homepage, https://k-oxon.github.io/estat_api_dlt_helper/
Project-URL: Repository, https://github.com/K-Oxon/estat_api_dlt_helper
Project-URL: Issues, https://github.com/K-Oxon/estat_api_dlt_helper/issues
Author-email: K-Oxon <ko1011qfp@gmail.com>
License-File: LICENSE
Keywords: api,dlt,e-stat,elt,estat,etl,helper
Classifier: Development Status :: 4 - Beta
Classifier: Intended Audience :: Developers
Classifier: License :: OSI Approved :: MIT License
Classifier: Programming Language :: Python :: 3
Classifier: Programming Language :: Python :: 3.11
Classifier: Programming Language :: Python :: 3.12
Classifier: Programming Language :: Python :: 3.13
Classifier: Topic :: Software Development :: Libraries
Requires-Python: >=3.11
Requires-Dist: dlt>=1.13.0
Requires-Dist: pyarrow>=20.0.0
Requires-Dist: pydantic>=2.11.7
Provides-Extra: athena
Requires-Dist: dlt[athena]; extra == 'athena'
Provides-Extra: bigquery
Requires-Dist: dlt[bigquery]; extra == 'bigquery'
Provides-Extra: duckdb
Requires-Dist: dlt[duckdb]; extra == 'duckdb'
Provides-Extra: filesystem
Requires-Dist: dlt[filesystem]; extra == 'filesystem'
Provides-Extra: motherduck
Requires-Dist: dlt[motherduck]; extra == 'motherduck'
Provides-Extra: redshift
Requires-Dist: dlt[redshift]; extra == 'redshift'
Provides-Extra: snowflake
Requires-Dist: dlt[snowflake]; extra == 'snowflake'
